classification/__init__.py
classification/base.py
classification/makes/carmake_dataset.py
classification/makes/finetuning_siglip.py
classification/makes/siglip_classifier.py
classification/objects/object_classifier.py
cli/__init__.py
cli/main.py
pipeline/__init__.py
pipeline/vision_pipeline.py
utils/__init__.py
utils/utils.py
pax_detector-0.1.7.dist-info/METADATA
pax_detector-0.1.7.dist-info/WHEEL
pax_detector-0.1.7.dist-info/entry_points.txt
pax_detector-0.1.7.dist-info/top_level.txt
pax_detector-0.1.7.dist-info/RECORD
