Metadata-Version: 2.4
Name: pax-detector
Version: 0.1.7
Summary: A vision pipeline for object and car make classification with CLI
Author-email: Gabriel Ayres <gabn2012@gmail.com>
License: MIT
Project-URL: Homepage, https://github.com/gabrielfnayres/pax-case
Project-URL: Repository, https://github.com/gabrielfnayres/pax-case
Keywords: computer-vision,object-detection,cli,yolo,vit
Classifier: Development Status :: 4 - Beta
Classifier: Intended Audience :: Developers
Classifier: License :: OSI Approved :: MIT License
Classifier: Programming Language :: Python :: 3
Classifier: Programming Language :: Python :: 3.10
Classifier: Topic :: Scientific/Engineering :: Image Recognition
Requires-Python: >=3.10
Requires-Dist: datasets>=4.0.0
Requires-Dist: fastapi[standard]>=0.116.1
Requires-Dist: gradio>=5.44.1
Requires-Dist: huggingface-hub>=0.34.4
Requires-Dist: opencv-python>=4.11.0.86
Requires-Dist: pathlib>=1.0.1
Requires-Dist: pillow>=11.3.0
Requires-Dist: pytorch-lightning>=2.5.3
Requires-Dist: rich>=14.1.0
Requires-Dist: scikit-learn>=1.7.1
Requires-Dist: tensorboardx>=2.6.4
Requires-Dist: torch>=2.8.0
Requires-Dist: torchaudio>=2.8.0
Requires-Dist: torchmetrics>=1.8.1
Requires-Dist: transformers>=4.55.4
Requires-Dist: ultralytics>=8.3.188
Requires-Dist: uvicorn>=0.35.0
